ifeval/__init__.py
ifeval/__main__.py
ifeval/core.py
ifeval-0.0.1.dist-info/METADATA
ifeval-0.0.1.dist-info/WHEEL
ifeval-0.0.1.dist-info/entry_points.txt
ifeval-0.0.1.dist-info/top_level.txt
ifeval-0.0.1.dist-info/RECORD
