Metadata-Version: 2.4
Name: ifeval
Version: 0.0.1
Summary: Evaluate all if-statement predicates in a Python file
Home-page: https://gitlab.com/knvvv/ifeval
Author: Nikolai Krivoshchapov
Classifier: Programming Language :: Python :: 3
Classifier: Operating System :: OS Independent
Requires-Python: >=3.8
Requires-Dist: libcst
Dynamic: author
Dynamic: classifier
Dynamic: description
Dynamic: description-content-type
Dynamic: home-page
Dynamic: requires-dist
Dynamic: requires-python
Dynamic: summary
